Metadata-Version: 2.1
Name: coordinate-finder
Version: 1.1
Summary: Package to find equidistant Lat & Long coordinates
Home-page: https://github.com/Alexterry101/MarsCoordFinder
Author: Alex Terry & Alistair Heath
Author-email: alexterry48@gmail.com.com
License: UNKNOWN
Platform: UNKNOWN
Classifier: Development Status :: 3 - Alpha
Classifier: Intended Audience :: Developers
Classifier: Programming Language :: Python :: 3
Classifier: License :: OSI Approved :: MIT License
Classifier: Operating System :: OS Independent
Requires-Python: >=3.6
